MANIFEST.in
README.md
VERSION
setup.py
aegisx.ext.oauth.egg-info/PKG-INFO
aegisx.ext.oauth.egg-info/SOURCES.txt
aegisx.ext.oauth.egg-info/dependency_links.txt
aegisx.ext.oauth.egg-info/requires.txt
aegisx.ext.oauth.egg-info/top_level.txt
aegisx/ext/oauth/__init__.py
aegisx/ext/oauth/const.py
aegisx/ext/oauth/fields.py
aegisx/ext/oauth/package.json
aegisx/ext/oauth/client/__init__.py
aegisx/ext/oauth/client/_client.py
aegisx/ext/oauth/client/_oidctokenvalidator.py
aegisx/ext/oauth/client/auth/__init__.py
aegisx/ext/oauth/client/auth/_baseresourceserver.py
aegisx/ext/oauth/client/auth/_clientsecretcredential.py
aegisx/ext/oauth/client/auth/_interactive.py
aegisx/ext/oauth/client/auth/_refreshtoken.py
aegisx/ext/oauth/client/repo/__init__.py
aegisx/ext/oauth/client/repo/_base.py
aegisx/ext/oauth/client/repo/_localclient.py
aegisx/ext/oauth/models/__init__.py
aegisx/ext/oauth/models/_accesstokentokenresponse.py
aegisx/ext/oauth/models/_authorizationcodegrant.py
aegisx/ext/oauth/models/_authorizationrequestparameters.py
aegisx/ext/oauth/models/_authorizationresponse.py
aegisx/ext/oauth/models/_authorizationresponsebase.py
aegisx/ext/oauth/models/_authorizationserverresponse.py
aegisx/ext/oauth/models/_clientconfiguration.py
aegisx/ext/oauth/models/_codeauthorizationresponse.py
aegisx/ext/oauth/models/_codeidtokenauthorizationresponse.py
aegisx/ext/oauth/models/_codeidtokentokenauthorizationresponse.py
aegisx/ext/oauth/models/_codetokenauthorizationresponse.py
aegisx/ext/oauth/models/_errorresponse.py
aegisx/ext/oauth/models/_fields.py
aegisx/ext/oauth/models/_grant.py
aegisx/ext/oauth/models/_idtokenauthorizationresponse.py
aegisx/ext/oauth/models/_idtokentokenauthorizationresponse.py
aegisx/ext/oauth/models/_jarmauthorizationresponse.py
aegisx/ext/oauth/models/_nonprotocolerrorresponse.py
aegisx/ext/oauth/models/_oidcclaimrequest.py
aegisx/ext/oauth/models/_oidcclaimspec.py
aegisx/ext/oauth/models/_oidcrequestedclaims.py
aegisx/ext/oauth/models/_oidctoken.py
aegisx/ext/oauth/models/_proofofpossessiontokenresponse.py
aegisx/ext/oauth/models/_refreshtokenrequest.py
aegisx/ext/oauth/models/_servermetadata.py
aegisx/ext/oauth/models/_tokenauthorizationresponse.py
